ehtml2text-2020.1.13.dist-info/DESCRIPTION.rst
ehtml2text-2020.1.13.dist-info/METADATA
ehtml2text-2020.1.13.dist-info/RECORD
ehtml2text-2020.1.13.dist-info/WHEEL
ehtml2text-2020.1.13.dist-info/entry_points.txt
ehtml2text-2020.1.13.dist-info/metadata.json
ehtml2text-2020.1.13.dist-info/top_level.txt
html2text/__init__.py
html2text/__main__.py
html2text/cli.py
html2text/compat.py
html2text/config.py
html2text/utils.py
