Metadata-Version: 2.0
Name: ehtml2text
Version: 2020.1.13
Summary: Turn HTML into equivalent Markdown-structured text.
Home-page: https://github.com/Alir3z4/html2text/
Author: Aaron Swartz
Author-email: me@aaronsw.com
Maintainer: Alireza Savand
Maintainer-email: alireza.savand@gmail.com
License: GNU GPL 3
Platform: OS Independent
Classifier: Development Status :: 5 - Production/Stable
Classifier: Intended Audience :: Developers
Classifier: License :: OSI Approved :: GNU General Public License (GPL)
Classifier: Operating System :: OS Independent
Classifier: Programming Language :: Python
Classifier: Programming Language :: Python :: 2
Classifier: Programming Language :: Python :: 2.7
Classifier: Programming Language :: Python :: 3
Classifier: Programming Language :: Python :: 3.4
Classifier: Programming Language :: Python :: 3.5
Classifier: Programming Language :: Python :: 3.6
Classifier: Programming Language :: Python :: 3.7
Classifier: Programming Language :: Python :: Implementation :: CPython
Classifier: Programming Language :: Python :: Implementation :: PyPy
Requires-Python: >=2.7, !=3.0.*, !=3.1.*, !=3.2.*, !=3.3.*
